{
    "id": "31651f336377d11d76b7a1ef5e7b457e",
    "name": "Heroku",
    "description": null,
    "auth": null,
    "events": null,
    "variables": [],
    "order": [],
    "folders_order": [],
    "folders": [],
    "requests": [
        {
            "id": "a96b0ad4a5761fe380f63212b4c5f5b9",
            "name": "Parameters Addons",
            "url": "httpsapi.heroku.com\/\/addons",
            "description": "Parameters addons.",
            "data": [],
            "dataMode": "raw",
            "headerData": null,
            "method": "parameters",
            "pathVariableData": [],
            "queryParams": [],
            "auth": null,
            "events": null,
            "folder": null,
            "protocolProfileBehavior": {
                "disableBodyPruning": true
            },
            "responses": [],
            "currentHelper": null,
            "helperAttributes": null,
            "collectionId": "31651f336377d11d76b7a1ef5e7b457e",
            "rawModeData": ""
        },
        {
            "id": "6a3bd79a493c1b311e495dbf1648dceb",
            "name": "Get Addons",
            "url": "httpsapi.heroku.com\/\/addons",
            "description": "List all available addons.",
            "data": [],
            "dataMode": "raw",
            "headerData": null,
            "method": "get",
            "pathVariableData": [],
            "queryParams": [
                {
                    "key": "Accept",
                    "description": "Content type.",
                    "value": "",
                    "equals": true,
                    "enabled": true
                },
                {
                    "key": "Accept",
                    "description": "Content type.",
                    "value": "",
                    "equals": true,
                    "enabled": true
                }
            ],
            "auth": null,
            "events": null,
            "folder": null,
            "protocolProfileBehavior": {
                "disableBodyPruning": true
            },
            "responses": [],
            "currentHelper": null,
            "helperAttributes": null,
            "collectionId": "31651f336377d11d76b7a1ef5e7b457e",
            "rawModeData": ""
        },
        {
            "id": "acc6a9efaa7f1b2ca1e24bbb0643d889",
            "name": "Parameter Application Addons",
            "url": "httpsapi.heroku.com\/\/apps\/{app}\/addons",
            "description": "Parameter application addons.",
            "data": [],
            "dataMode": "raw",
            "headerData": null,
            "method": "parameters",
            "pathVariableData": [],
            "queryParams": [],
            "auth": null,
            "events": null,
            "folder": null,
            "protocolProfileBehavior": {
                "disableBodyPruning": true
            },
            "responses": [],
            "currentHelper": null,
            "helperAttributes": null,
            "collectionId": "31651f336377d11d76b7a1ef5e7b457e",
            "rawModeData": ""
        },
        {
            "id": "a1875b0322e646bf5b881987e8932da3",
            "name": "Get Application Addons",
            "url": "httpsapi.heroku.com\/\/apps\/{app}\/addons",
            "description": "List addons installed on an app.",
            "data": [],
            "dataMode": "raw",
            "headerData": null,
            "method": "get",
            "pathVariableData": [],
            "queryParams": [
                {
                    "key": "Accept",
                    "description": "Content type.",
                    "value": "",
                    "equals": true,
                    "enabled": true
                },
                {
                    "key": "Accept",
                    "description": "Content type.",
                    "value": "",
                    "equals": true,
                    "enabled": true
                },
                {
                    "key": "app",
                    "description": "The app name.",
                    "value": "",
                    "equals": true,
                    "enabled": true
                },
                {
                    "key": "app",
                    "description": "",
                    "value": "",
                    "equals": true,
                    "enabled": true
                }
            ],
            "auth": null,
            "events": null,
            "folder": null,
            "protocolProfileBehavior": {
                "disableBodyPruning": true
            },
            "responses": [],
            "currentHelper": null,
            "helperAttributes": null,
            "collectionId": "31651f336377d11d76b7a1ef5e7b457e",
            "rawModeData": ""
        },
        {
            "id": "4705e1c4f8c08a37d686354fbb1ed500",
            "name": "Parameters Applications Addons",
            "url": "httpsapi.heroku.com\/\/apps\/{app}\/addons\/{addon}",
            "description": "Parameters applications addons.",
            "data": [],
            "dataMode": "raw",
            "headerData": null,
            "method": "parameters",
            "pathVariableData": [],
            "queryParams": [],
            "auth": null,
            "events": null,
            "folder": null,
            "protocolProfileBehavior": {
                "disableBodyPruning": true
            },
            "responses": [],
            "currentHelper": null,
            "helperAttributes": null,
            "collectionId": "31651f336377d11d76b7a1ef5e7b457e",
            "rawModeData": ""
        },
        {
            "id": "fb8a01d69276aedfaa072197723e0cdc",
            "name": "Add Application Addons",
            "url": "httpsapi.heroku.com\/\/apps\/{app}\/addons\/{addon}",
            "description": "Install an addon to an app.",
            "data": [],
            "dataMode": "raw",
            "headerData": null,
            "method": "post",
            "pathVariableData": [],
            "queryParams": [
                {
                    "key": "Accept",
                    "description": "Content type.",
                    "value": "",
                    "equals": true,
                    "enabled": true
                },
                {
                    "key": "Accept",
                    "description": "Content type.",
                    "value": "",
                    "equals": true,
                    "enabled": true
                },
                {
                    "key": "addon",
                    "description": "the addon name.",
                    "value": "",
                    "equals": true,
                    "enabled": true
                },
                {
                    "key": "addon",
                    "description": "",
                    "value": "",
                    "equals": true,
                    "enabled": true
                },
                {
                    "key": "app",
                    "description": "The app name.",
                    "value": "",
                    "equals": true,
                    "enabled": true
                },
                {
                    "key": "app",
                    "description": "",
                    "value": "",
                    "equals": true,
                    "enabled": true
                }
            ],
            "auth": null,
            "events": null,
            "folder": null,
            "protocolProfileBehavior": {
                "disableBodyPruning": true
            },
            "responses": [],
            "currentHelper": null,
            "helperAttributes": null,
            "collectionId": "31651f336377d11d76b7a1ef5e7b457e",
            "rawModeData": ""
        },
        {
            "id": "e3b590dde872986bc72c5fd95fb0699e",
            "name": "Put Application Addons",
            "url": "httpsapi.heroku.com\/\/apps\/{app}\/addons\/{addon}",
            "description": "Upgrade an addon to an app.",
            "data": [],
            "dataMode": "raw",
            "headerData": null,
            "method": "put",
            "pathVariableData": [],
            "queryParams": [
                {
                    "key": "Accept",
                    "description": "Content type.",
                    "value": "",
                    "equals": true,
                    "enabled": true
                },
                {
                    "key": "Accept",
                    "description": "Content type.",
                    "value": "",
                    "equals": true,
                    "enabled": true
                },
                {
                    "key": "addon",
                    "description": "the addon name.",
                    "value": "",
                    "equals": true,
                    "enabled": true
                },
                {
                    "key": "addon",
                    "description": "",
                    "value": "",
                    "equals": true,
                    "enabled": true
                },
                {
                    "key": "app",
                    "description": "The app name.",
                    "value": "",
                    "equals": true,
                    "enabled": true
                },
                {
                    "key": "app",
                    "description": "",
                    "value": "",
                    "equals": true,
                    "enabled": true
                }
            ],
            "auth": null,
            "events": null,
            "folder": null,
            "protocolProfileBehavior": {
                "disableBodyPruning": true
            },
            "responses": [],
            "currentHelper": null,
            "helperAttributes": null,
            "collectionId": "31651f336377d11d76b7a1ef5e7b457e",
            "rawModeData": ""
        },
        {
            "id": "675cff4ad8529112b9ba805208d60924",
            "name": "Delete Applications Addons",
            "url": "httpsapi.heroku.com\/\/apps\/{app}\/addons\/{addon}",
            "description": "Uninstall an addon from an app.",
            "data": [],
            "dataMode": "raw",
            "headerData": null,
            "method": "delete",
            "pathVariableData": [],
            "queryParams": [
                {
                    "key": "Accept",
                    "description": "Content type.",
                    "value": "",
                    "equals": true,
                    "enabled": true
                },
                {
                    "key": "Accept",
                    "description": "Content type.",
                    "value": "",
                    "equals": true,
                    "enabled": true
                },
                {
                    "key": "addon",
                    "description": "the addon name.",
                    "value": "",
                    "equals": true,
                    "enabled": true
                },
                {
                    "key": "addon",
                    "description": "",
                    "value": "",
                    "equals": true,
                    "enabled": true
                },
                {
                    "key": "app",
                    "description": "The app name.",
                    "value": "",
                    "equals": true,
                    "enabled": true
                },
                {
                    "key": "app",
                    "description": "",
                    "value": "",
                    "equals": true,
                    "enabled": true
                }
            ],
            "auth": null,
            "events": null,
            "folder": null,
            "protocolProfileBehavior": {
                "disableBodyPruning": true
            },
            "responses": [],
            "currentHelper": null,
            "helperAttributes": null,
            "collectionId": "31651f336377d11d76b7a1ef5e7b457e",
            "rawModeData": ""
        },
        {
            "id": "48e14b5a5e7026c06178a8f6f9c0568e",
            "name": "Parameters Applications",
            "url": "httpsapi.heroku.com\/\/apps",
            "description": "Parameters applications.",
            "data": [],
            "dataMode": "raw",
            "headerData": null,
            "method": "parameters",
            "pathVariableData": [],
            "queryParams": [],
            "auth": null,
            "events": null,
            "folder": null,
            "protocolProfileBehavior": {
                "disableBodyPruning": true
            },
            "responses": [],
            "currentHelper": null,
            "helperAttributes": null,
            "collectionId": "31651f336377d11d76b7a1ef5e7b457e",
            "rawModeData": ""
        },
        {
            "id": "5449e8200468994e54dad3662628dfdd",
            "name": "Get Applications",
            "url": "httpsapi.heroku.com\/\/apps",
            "description": "Get applications.",
            "data": [],
            "dataMode": "raw",
            "headerData": null,
            "method": "get",
            "pathVariableData": [],
            "queryParams": [
                {
                    "key": "Accept",
                    "description": "Content type.",
                    "value": "",
                    "equals": true,
                    "enabled": true
                },
                {
                    "key": "Accept",
                    "description": "Content type.",
                    "value": "",
                    "equals": true,
                    "enabled": true
                }
            ],
            "auth": null,
            "events": null,
            "folder": null,
            "protocolProfileBehavior": {
                "disableBodyPruning": true
            },
            "responses": [],
            "currentHelper": null,
            "helperAttributes": null,
            "collectionId": "31651f336377d11d76b7a1ef5e7b457e",
            "rawModeData": ""
        },
        {
            "id": "ae767271aa399e02e801dcb99e420ae1",
            "name": "Add Applications",
            "url": "httpsapi.heroku.com\/\/apps",
            "description": "Add applications.",
            "data": [],
            "dataMode": "raw",
            "headerData": null,
            "method": "post",
            "pathVariableData": [],
            "queryParams": [
                {
                    "key": "Accept",
                    "description": "Content type.",
                    "value": "",
                    "equals": true,
                    "enabled": true
                },
                {
                    "key": "Accept",
                    "description": "Content type.",
                    "value": "",
                    "equals": true,
                    "enabled": true
                }
            ],
            "auth": null,
            "events": null,
            "folder": null,
            "protocolProfileBehavior": {
                "disableBodyPruning": true
            },
            "responses": [],
            "currentHelper": null,
            "helperAttributes": null,
            "collectionId": "31651f336377d11d76b7a1ef5e7b457e",
            "rawModeData": ""
        },
        {
            "id": "eb6c09b65371e7989c437ca8c5f0bb90",
            "name": "Parameters Applications Name",
            "url": "httpsapi.heroku.com\/\/apps\/{name}",
            "description": "Parameters applications name.",
            "data": [],
            "dataMode": "raw",
            "headerData": null,
            "method": "parameters",
            "pathVariableData": [],
            "queryParams": [],
            "auth": null,
            "events": null,
            "folder": null,
            "protocolProfileBehavior": {
                "disableBodyPruning": true
            },
            "responses": [],
            "currentHelper": null,
            "helperAttributes": null,
            "collectionId": "31651f336377d11d76b7a1ef5e7b457e",
            "rawModeData": ""
        },
        {
            "id": "daa1571bd09b43286e688b000144f7fd",
            "name": "Get Applications Name",
            "url": "httpsapi.heroku.com\/\/apps\/{name}",
            "description": "Get applications name.",
            "data": [],
            "dataMode": "raw",
            "headerData": null,
            "method": "get",
            "pathVariableData": [],
            "queryParams": [
                {
                    "key": "Accept",
                    "description": "Content type.",
                    "value": "",
                    "equals": true,
                    "enabled": true
                },
                {
                    "key": "Accept",
                    "description": "Content type.",
                    "value": "",
                    "equals": true,
                    "enabled": true
                },
                {
                    "key": "name",
                    "description": "The app name.",
                    "value": "",
                    "equals": true,
                    "enabled": true
                },
                {
                    "key": "name",
                    "description": "",
                    "value": "",
                    "equals": true,
                    "enabled": true
                }
            ],
            "auth": null,
            "events": null,
            "folder": null,
            "protocolProfileBehavior": {
                "disableBodyPruning": true
            },
            "responses": [],
            "currentHelper": null,
            "helperAttributes": null,
            "collectionId": "31651f336377d11d76b7a1ef5e7b457e",
            "rawModeData": ""
        },
        {
            "id": "d8added2f893ec3f72488459f2a51bf8",
            "name": "Delete Applications Name",
            "url": "httpsapi.heroku.com\/\/apps\/{name}",
            "description": "Delete applications name.",
            "data": [],
            "dataMode": "raw",
            "headerData": null,
            "method": "delete",
            "pathVariableData": [],
            "queryParams": [
                {
                    "key": "Accept",
                    "description": "Content type.",
                    "value": "",
                    "equals": true,
                    "enabled": true
                },
                {
                    "key": "Accept",
                    "description": "Content type.",
                    "value": "",
                    "equals": true,
                    "enabled": true
                },
                {
                    "key": "name",
                    "description": "The app name.",
                    "value": "",
                    "equals": true,
                    "enabled": true
                },
                {
                    "key": "name",
                    "description": "",
                    "value": "",
                    "equals": true,
                    "enabled": true
                }
            ],
            "auth": null,
            "events": null,
            "folder": null,
            "protocolProfileBehavior": {
                "disableBodyPruning": true
            },
            "responses": [],
            "currentHelper": null,
            "helperAttributes": null,
            "collectionId": "31651f336377d11d76b7a1ef5e7b457e",
            "rawModeData": ""
        },
        {
            "id": "379eb749206a0a1abe57412ec6c54143",
            "name": "Parameters Application Collaborators",
            "url": "httpsapi.heroku.com\/\/apps\/{app}\/collaborators",
            "description": "Parameters application collaborators.",
            "data": [],
            "dataMode": "raw",
            "headerData": null,
            "method": "parameters",
            "pathVariableData": [],
            "queryParams": [],
            "auth": null,
            "events": null,
            "folder": null,
            "protocolProfileBehavior": {
                "disableBodyPruning": true
            },
            "responses": [],
            "currentHelper": null,
            "helperAttributes": null,
            "collectionId": "31651f336377d11d76b7a1ef5e7b457e",
            "rawModeData": ""
        },
        {
            "id": "653fba6c351e39203f6e8958ac1a3976",
            "name": "Get Application Collaborators",
            "url": "httpsapi.heroku.com\/\/apps\/{app}\/collaborators",
            "description": "List collaborators for an app.",
            "data": [],
            "dataMode": "raw",
            "headerData": null,
            "method": "get",
            "pathVariableData": [],
            "queryParams": [
                {
                    "key": "Accept",
                    "description": "Content type.",
                    "value": "",
                    "equals": true,
                    "enabled": true
                },
                {
                    "key": "Accept",
                    "description": "Content type.",
                    "value": "",
                    "equals": true,
                    "enabled": true
                },
                {
                    "key": "app",
                    "description": "The app name.",
                    "value": "",
                    "equals": true,
                    "enabled": true
                },
                {
                    "key": "app",
                    "description": "",
                    "value": "",
                    "equals": true,
                    "enabled": true
                }
            ],
            "auth": null,
            "events": null,
            "folder": null,
            "protocolProfileBehavior": {
                "disableBodyPruning": true
            },
            "responses": [],
            "currentHelper": null,
            "helperAttributes": null,
            "collectionId": "31651f336377d11d76b7a1ef5e7b457e",
            "rawModeData": ""
        },
        {
            "id": "5d3019e642ef2a596e103ddf9e147c92",
            "name": "Parameters Application Collaborators Email",
            "url": "httpsapi.heroku.com\/\/apps\/{app}\/collaborators\/{email}",
            "description": "Parameters application collaborators email.",
            "data": [],
            "dataMode": "raw",
            "headerData": null,
            "method": "parameters",
            "pathVariableData": [],
            "queryParams": [],
            "auth": null,
            "events": null,
            "folder": null,
            "protocolProfileBehavior": {
                "disableBodyPruning": true
            },
            "responses": [],
            "currentHelper": null,
            "helperAttributes": null,
            "collectionId": "31651f336377d11d76b7a1ef5e7b457e",
            "rawModeData": ""
        },
        {
            "id": "e432dae3788227a6fbe7b3f0d78e7b55",
            "name": "Delete Application Collaborators Email",
            "url": "httpsapi.heroku.com\/\/apps\/{app}\/collaborators\/{email}",
            "description": "Delete application collaborators email.",
            "data": [],
            "dataMode": "raw",
            "headerData": null,
            "method": "delete",
            "pathVariableData": [],
            "queryParams": [
                {
                    "key": "Accept",
                    "description": "Content type.",
                    "value": "",
                    "equals": true,
                    "enabled": true
                },
                {
                    "key": "Accept",
                    "description": "Content type.",
                    "value": "",
                    "equals": true,
                    "enabled": true
                },
                {
                    "key": "app",
                    "description": "The app name.",
                    "value": "",
                    "equals": true,
                    "enabled": true
                },
                {
                    "key": "app",
                    "description": "",
                    "value": "",
                    "equals": true,
                    "enabled": true
                },
                {
                    "key": "email",
                    "description": "The email of the user to remove as a collaborator.",
                    "value": "",
                    "equals": true,
                    "enabled": true
                },
                {
                    "key": "email",
                    "description": "",
                    "value": "",
                    "equals": true,
                    "enabled": true
                }
            ],
            "auth": null,
            "events": null,
            "folder": null,
            "protocolProfileBehavior": {
                "disableBodyPruning": true
            },
            "responses": [],
            "currentHelper": null,
            "helperAttributes": null,
            "collectionId": "31651f336377d11d76b7a1ef5e7b457e",
            "rawModeData": ""
        },
        {
            "id": "4be44c145af5372cab71bdeae5cc0cfb",
            "name": "Parameters Application Config Variables",
            "url": "httpsapi.heroku.com\/\/apps\/{app}\/config_vars",
            "description": "Parameters application config variables.",
            "data": [],
            "dataMode": "raw",
            "headerData": null,
            "method": "parameters",
            "pathVariableData": [],
            "queryParams": [],
            "auth": null,
            "events": null,
            "folder": null,
            "protocolProfileBehavior": {
                "disableBodyPruning": true
            },
            "responses": [],
            "currentHelper": null,
            "helperAttributes": null,
            "collectionId": "31651f336377d11d76b7a1ef5e7b457e",
            "rawModeData": ""
        },
        {
            "id": "53b0ecbd364626046d93583718b02461",
            "name": "Get Application Config Variables",
            "url": "httpsapi.heroku.com\/\/apps\/{app}\/config_vars",
            "description": "Get application config variables.",
            "data": [],
            "dataMode": "raw",
            "headerData": null,
            "method": "get",
            "pathVariableData": [],
            "queryParams": [
                {
                    "key": "Accept",
                    "description": "Content type.",
                    "value": "",
                    "equals": true,
                    "enabled": true
                },
                {
                    "key": "Accept",
                    "description": "Content type.",
                    "value": "",
                    "equals": true,
                    "enabled": true
                },
                {
                    "key": "app",
                    "description": "The app name.",
                    "value": "",
                    "equals": true,
                    "enabled": true
                },
                {
                    "key": "app",
                    "description": "",
                    "value": "",
                    "equals": true,
                    "enabled": true
                }
            ],
            "auth": null,
            "events": null,
            "folder": null,
            "protocolProfileBehavior": {
                "disableBodyPruning": true
            },
            "responses": [],
            "currentHelper": null,
            "helperAttributes": null,
            "collectionId": "31651f336377d11d76b7a1ef5e7b457e",
            "rawModeData": ""
        },
        {
            "id": "76b84455001c27d40f76e427c639bc9c",
            "name": "Put Application Config Variables",
            "url": "httpsapi.heroku.com\/\/apps\/{app}\/config_vars",
            "description": "Put application config variables.",
            "data": [],
            "dataMode": "raw",
            "headerData": null,
            "method": "put",
            "pathVariableData": [],
            "queryParams": [
                {
                    "key": "Accept",
                    "description": "Content type.",
                    "value": "",
                    "equals": true,
                    "enabled": true
                },
                {
                    "key": "Accept",
                    "description": "Content type.",
                    "value": "",
                    "equals": true,
                    "enabled": true
                },
                {
                    "key": "app",
                    "description": "The app name.",
                    "value": "",
                    "equals": true,
                    "enabled": true
                },
                {
                    "key": "app",
                    "description": "",
                    "value": "",
                    "equals": true,
                    "enabled": true
                }
            ],
            "auth": null,
            "events": null,
            "folder": null,
            "protocolProfileBehavior": {
                "disableBodyPruning": true
            },
            "responses": [],
            "currentHelper": null,
            "helperAttributes": null,
            "collectionId": "31651f336377d11d76b7a1ef5e7b457e",
            "rawModeData": ""
        },
        {
            "id": "fbdbee9b8056517aa793979760f38081",
            "name": "Parameters Application Config Variables Key",
            "url": "httpsapi.heroku.com\/\/apps\/{app}\/config_vars\/{key}",
            "description": "Parameters application config variables key.",
            "data": [],
            "dataMode": "raw",
            "headerData": null,
            "method": "parameters",
            "pathVariableData": [],
            "queryParams": [],
            "auth": null,
            "events": null,
            "folder": null,
            "protocolProfileBehavior": {
                "disableBodyPruning": true
            },
            "responses": [],
            "currentHelper": null,
            "helperAttributes": null,
            "collectionId": "31651f336377d11d76b7a1ef5e7b457e",
            "rawModeData": ""
        },
        {
            "id": "7cf9281b0aec54b09d9e3d2159dcf0dc",
            "name": "Delete Application Config Variables Key",
            "url": "httpsapi.heroku.com\/\/apps\/{app}\/config_vars\/{key}",
            "description": "Delete application config variables key.",
            "data": [],
            "dataMode": "raw",
            "headerData": null,
            "method": "delete",
            "pathVariableData": [],
            "queryParams": [
                {
                    "key": "Accept",
                    "description": "Content type.",
                    "value": "",
                    "equals": true,
                    "enabled": true
                },
                {
                    "key": "Accept",
                    "description": "Content type.",
                    "value": "",
                    "equals": true,
                    "enabled": true
                },
                {
                    "key": "app",
                    "description": "The app name.",
                    "value": "",
                    "equals": true,
                    "enabled": true
                },
                {
                    "key": "app",
                    "description": "",
                    "value": "",
                    "equals": true,
                    "enabled": true
                },
                {
                    "key": "key",
                    "description": "The config var to remove.",
                    "value": "",
                    "equals": true,
                    "enabled": true
                },
                {
                    "key": "key",
                    "description": "",
                    "value": "",
                    "equals": true,
                    "enabled": true
                }
            ],
            "auth": null,
            "events": null,
            "folder": null,
            "protocolProfileBehavior": {
                "disableBodyPruning": true
            },
            "responses": [],
            "currentHelper": null,
            "helperAttributes": null,
            "collectionId": "31651f336377d11d76b7a1ef5e7b457e",
            "rawModeData": ""
        },
        {
            "id": "74f8df5eb6c3cdab773130eac4eaac20",
            "name": "Parameters Application Domains",
            "url": "httpsapi.heroku.com\/\/apps\/{app}\/domains",
            "description": "Parameters application domains.",
            "data": [],
            "dataMode": "raw",
            "headerData": null,
            "method": "parameters",
            "pathVariableData": [],
            "queryParams": [],
            "auth": null,
            "events": null,
            "folder": null,
            "protocolProfileBehavior": {
                "disableBodyPruning": true
            },
            "responses": [],
            "currentHelper": null,
            "helperAttributes": null,
            "collectionId": "31651f336377d11d76b7a1ef5e7b457e",
            "rawModeData": ""
        },
        {
            "id": "ebab1a0e35b59d34b805625d47c4380c",
            "name": "Get Application Domains",
            "url": "httpsapi.heroku.com\/\/apps\/{app}\/domains",
            "description": "List domains for an app.",
            "data": [],
            "dataMode": "raw",
            "headerData": null,
            "method": "get",
            "pathVariableData": [],
            "queryParams": [
                {
                    "key": "Accept",
                    "description": "Content type.",
                    "value": "",
                    "equals": true,
                    "enabled": true
                },
                {
                    "key": "Accept",
                    "description": "Content type.",
                    "value": "",
                    "equals": true,
                    "enabled": true
                },
                {
                    "key": "app",
                    "description": "The app name.",
                    "value": "",
                    "equals": true,
                    "enabled": true
                },
                {
                    "key": "app",
                    "description": "",
                    "value": "",
                    "equals": true,
                    "enabled": true
                }
            ],
            "auth": null,
            "events": null,
            "folder": null,
            "protocolProfileBehavior": {
                "disableBodyPruning": true
            },
            "responses": [],
            "currentHelper": null,
            "helperAttributes": null,
            "collectionId": "31651f336377d11d76b7a1ef5e7b457e",
            "rawModeData": ""
        },
        {
            "id": "3b95678744baa22f182f0c52462ad8eb",
            "name": "Parameters Application Domain Name",
            "url": "httpsapi.heroku.com\/\/apps\/{app}\/domains\/{domain_name}",
            "description": "Parameters application domain name.",
            "data": [],
            "dataMode": "raw",
            "headerData": null,
            "method": "parameters",
            "pathVariableData": [],
            "queryParams": [],
            "auth": null,
            "events": null,
            "folder": null,
            "protocolProfileBehavior": {
                "disableBodyPruning": true
            },
            "responses": [],
            "currentHelper": null,
            "helperAttributes": null,
            "collectionId": "31651f336377d11d76b7a1ef5e7b457e",
            "rawModeData": ""
        },
        {
            "id": "a4f013342e2331946f876c40c15e4e9d",
            "name": "Delete Application Domain Name",
            "url": "httpsapi.heroku.com\/\/apps\/{app}\/domains\/{domain_name}",
            "description": "Delete application domain name.",
            "data": [],
            "dataMode": "raw",
            "headerData": null,
            "method": "delete",
            "pathVariableData": [],
            "queryParams": [
                {
                    "key": "Accept",
                    "description": "Content type.",
                    "value": "",
                    "equals": true,
                    "enabled": true
                },
                {
                    "key": "Accept",
                    "description": "Content type.",
                    "value": "",
                    "equals": true,
                    "enabled": true
                },
                {
                    "key": "app",
                    "description": "The app name.",
                    "value": "",
                    "equals": true,
                    "enabled": true
                },
                {
                    "key": "app",
                    "description": "",
                    "value": "",
                    "equals": true,
                    "enabled": true
                },
                {
                    "key": "domain_name",
                    "description": "The domain to remove.",
                    "value": "",
                    "equals": true,
                    "enabled": true
                },
                {
                    "key": "domain_name",
                    "description": "",
                    "value": "",
                    "equals": true,
                    "enabled": true
                }
            ],
            "auth": null,
            "events": null,
            "folder": null,
            "protocolProfileBehavior": {
                "disableBodyPruning": true
            },
            "responses": [],
            "currentHelper": null,
            "helperAttributes": null,
            "collectionId": "31651f336377d11d76b7a1ef5e7b457e",
            "rawModeData": ""
        },
        {
            "id": "529b577f9ae2665c85adf492f76ffa50",
            "name": "Parameters User Keys",
            "url": "httpsapi.heroku.com\/\/user\/keys",
            "description": "Parameters user keys.",
            "data": [],
            "dataMode": "raw",
            "headerData": null,
            "method": "parameters",
            "pathVariableData": [],
            "queryParams": [],
            "auth": null,
            "events": null,
            "folder": null,
            "protocolProfileBehavior": {
                "disableBodyPruning": true
            },
            "responses": [],
            "currentHelper": null,
            "helperAttributes": null,
            "collectionId": "31651f336377d11d76b7a1ef5e7b457e",
            "rawModeData": ""
        },
        {
            "id": "896d21bf82235df7aa1811d851fdaf75",
            "name": "Get User Keys",
            "url": "httpsapi.heroku.com\/\/user\/keys",
            "description": "List SSH keys.",
            "data": [],
            "dataMode": "raw",
            "headerData": null,
            "method": "get",
            "pathVariableData": [],
            "queryParams": [
                {
                    "key": "Accept",
                    "description": "Content type.",
                    "value": "",
                    "equals": true,
                    "enabled": true
                },
                {
                    "key": "Accept",
                    "description": "Content type.",
                    "value": "",
                    "equals": true,
                    "enabled": true
                }
            ],
            "auth": null,
            "events": null,
            "folder": null,
            "protocolProfileBehavior": {
                "disableBodyPruning": true
            },
            "responses": [],
            "currentHelper": null,
            "helperAttributes": null,
            "collectionId": "31651f336377d11d76b7a1ef5e7b457e",
            "rawModeData": ""
        },
        {
            "id": "9825cc7b6e2ae4dbf518c2c272ef945d",
            "name": "Add User Keys",
            "url": "httpsapi.heroku.com\/\/user\/keys",
            "description": "Associate an SSH key with this account.",
            "data": [],
            "dataMode": "raw",
            "headerData": null,
            "method": "post",
            "pathVariableData": [],
            "queryParams": [
                {
                    "key": "Accept",
                    "description": "Content type.",
                    "value": "",
                    "equals": true,
                    "enabled": true
                },
                {
                    "key": "Accept",
                    "description": "Content type.",
                    "value": "",
                    "equals": true,
                    "enabled": true
                }
            ],
            "auth": null,
            "events": null,
            "folder": null,
            "protocolProfileBehavior": {
                "disableBodyPruning": true
            },
            "responses": [],
            "currentHelper": null,
            "helperAttributes": null,
            "collectionId": "31651f336377d11d76b7a1ef5e7b457e",
            "rawModeData": ""
        },
        {
            "id": "1f80887d2336c9362d40f36b7ed6c1c7",
            "name": "Parameters User Keys Key",
            "url": "httpsapi.heroku.com\/\/user\/keys\/{key}",
            "description": "Parameters user keys key.",
            "data": [],
            "dataMode": "raw",
            "headerData": null,
            "method": "parameters",
            "pathVariableData": [],
            "queryParams": [],
            "auth": null,
            "events": null,
            "folder": null,
            "protocolProfileBehavior": {
                "disableBodyPruning": true
            },
            "responses": [],
            "currentHelper": null,
            "helperAttributes": null,
            "collectionId": "31651f336377d11d76b7a1ef5e7b457e",
            "rawModeData": ""
        },
        {
            "id": "db9a8713fd00045713eb2952f53d82c1",
            "name": "Delete User Keys Key",
            "url": "httpsapi.heroku.com\/\/user\/keys\/{key}",
            "description": "Remove an SSH key from this account.",
            "data": [],
            "dataMode": "raw",
            "headerData": null,
            "method": "delete",
            "pathVariableData": [],
            "queryParams": [
                {
                    "key": "Accept",
                    "description": "Content type.",
                    "value": "",
                    "equals": true,
                    "enabled": true
                },
                {
                    "key": "Accept",
                    "description": "Content type.",
                    "value": "",
                    "equals": true,
                    "enabled": true
                },
                {
                    "key": "key",
                    "description": "The config var to remove.",
                    "value": "",
                    "equals": true,
                    "enabled": true
                },
                {
                    "key": "key",
                    "description": "",
                    "value": "",
                    "equals": true,
                    "enabled": true
                }
            ],
            "auth": null,
            "events": null,
            "folder": null,
            "protocolProfileBehavior": {
                "disableBodyPruning": true
            },
            "responses": [],
            "currentHelper": null,
            "helperAttributes": null,
            "collectionId": "31651f336377d11d76b7a1ef5e7b457e",
            "rawModeData": ""
        },
        {
            "id": "c008ad25cd5c7498ef573b4b832de1c2",
            "name": "Parameters Application Logs",
            "url": "httpsapi.heroku.com\/\/apps\/{app}\/logs",
            "description": "Parameters application logs.",
            "data": [],
            "dataMode": "raw",
            "headerData": null,
            "method": "parameters",
            "pathVariableData": [],
            "queryParams": [],
            "auth": null,
            "events": null,
            "folder": null,
            "protocolProfileBehavior": {
                "disableBodyPruning": true
            },
            "responses": [],
            "currentHelper": null,
            "helperAttributes": null,
            "collectionId": "31651f336377d11d76b7a1ef5e7b457e",
            "rawModeData": ""
        },
        {
            "id": "b3f07a9227734bdf93fa2da265f9a8ac",
            "name": "Get Application Logs",
            "url": "httpsapi.heroku.com\/\/apps\/{app}\/logs",
            "description": "Get application logs.",
            "data": [],
            "dataMode": "raw",
            "headerData": null,
            "method": "get",
            "pathVariableData": [],
            "queryParams": [
                {
                    "key": "Accept",
                    "description": "Content type.",
                    "value": "",
                    "equals": true,
                    "enabled": true
                },
                {
                    "key": "Accept",
                    "description": "Content type.",
                    "value": "",
                    "equals": true,
                    "enabled": true
                },
                {
                    "key": "app",
                    "description": "The app name.",
                    "value": "",
                    "equals": true,
                    "enabled": true
                },
                {
                    "key": "app",
                    "description": "",
                    "value": "",
                    "equals": true,
                    "enabled": true
                },
                {
                    "key": "logplex",
                    "description": "Use logplex to stream logs (always true).",
                    "value": "",
                    "equals": true,
                    "enabled": true
                },
                {
                    "key": "num",
                    "description": "The number of lines to display.",
                    "value": "",
                    "equals": true,
                    "enabled": true
                },
                {
                    "key": "ps",
                    "description": "Only display logs from a given process.",
                    "value": "",
                    "equals": true,
                    "enabled": true
                },
                {
                    "key": "source",
                    "description": "Only display logs from a given source.",
                    "value": "",
                    "equals": true,
                    "enabled": true
                },
                {
                    "key": "tail",
                    "description": "1: continually stream logs - : display only num logs",
                    "value": "",
                    "equals": true,
                    "enabled": true
                }
            ],
            "auth": null,
            "events": null,
            "folder": null,
            "protocolProfileBehavior": {
                "disableBodyPruning": true
            },
            "responses": [],
            "currentHelper": null,
            "helperAttributes": null,
            "collectionId": "31651f336377d11d76b7a1ef5e7b457e",
            "rawModeData": ""
        },
        {
            "id": "88cee769830ba7020eb4a101f7d02e10",
            "name": "Parameters Application PS",
            "url": "httpsapi.heroku.com\/\/apps\/{app}\/ps",
            "description": "Parameters application ps.",
            "data": [],
            "dataMode": "raw",
            "headerData": null,
            "method": "parameters",
            "pathVariableData": [],
            "queryParams": [],
            "auth": null,
            "events": null,
            "folder": null,
            "protocolProfileBehavior": {
                "disableBodyPruning": true
            },
            "responses": [],
            "currentHelper": null,
            "helperAttributes": null,
            "collectionId": "31651f336377d11d76b7a1ef5e7b457e",
            "rawModeData": ""
        },
        {
            "id": "ca29ec310211d0dc40931b34395bac7c",
            "name": "Get Application PS",
            "url": "httpsapi.heroku.com\/\/apps\/{app}\/ps",
            "description": "List processes for an app.",
            "data": [],
            "dataMode": "raw",
            "headerData": null,
            "method": "get",
            "pathVariableData": [],
            "queryParams": [
                {
                    "key": "Accept",
                    "description": "Content type.",
                    "value": "",
                    "equals": true,
                    "enabled": true
                },
                {
                    "key": "Accept",
                    "description": "Content type.",
                    "value": "",
                    "equals": true,
                    "enabled": true
                },
                {
                    "key": "app",
                    "description": "The app name.",
                    "value": "",
                    "equals": true,
                    "enabled": true
                },
                {
                    "key": "app",
                    "description": "",
                    "value": "",
                    "equals": true,
                    "enabled": true
                }
            ],
            "auth": null,
            "events": null,
            "folder": null,
            "protocolProfileBehavior": {
                "disableBodyPruning": true
            },
            "responses": [],
            "currentHelper": null,
            "helperAttributes": null,
            "collectionId": "31651f336377d11d76b7a1ef5e7b457e",
            "rawModeData": ""
        },
        {
            "id": "d26bbb51b7a6a40aa8357b8571e818c2",
            "name": "Add Application PS",
            "url": "httpsapi.heroku.com\/\/apps\/{app}\/ps",
            "description": "Run a one-off process.",
            "data": [],
            "dataMode": "raw",
            "headerData": null,
            "method": "post",
            "pathVariableData": [],
            "queryParams": [
                {
                    "key": "Accept",
                    "description": "Content type.",
                    "value": "",
                    "equals": true,
                    "enabled": true
                },
                {
                    "key": "command",
                    "description": "The command to run.",
                    "value": "",
                    "equals": true,
                    "enabled": true
                },
                {
                    "key": "attach",
                    "description": "true: use rendezvous to access stdin\/stdout - <blank>: stream process output to the application log",
                    "value": "",
                    "equals": true,
                    "enabled": true
                },
                {
                    "key": "Accept",
                    "description": "Content type.",
                    "value": "",
                    "equals": true,
                    "enabled": true
                },
                {
                    "key": "app",
                    "description": "The app name.",
                    "value": "",
                    "equals": true,
                    "enabled": true
                },
                {
                    "key": "app",
                    "description": "",
                    "value": "",
                    "equals": true,
                    "enabled": true
                }
            ],
            "auth": null,
            "events": null,
            "folder": null,
            "protocolProfileBehavior": {
                "disableBodyPruning": true
            },
            "responses": [],
            "currentHelper": null,
            "helperAttributes": null,
            "collectionId": "31651f336377d11d76b7a1ef5e7b457e",
            "rawModeData": ""
        },
        {
            "id": "6438565ae57656b10912e6da39684a90",
            "name": "Parameters Application PS Restart",
            "url": "httpsapi.heroku.com\/\/apps\/{app}\/ps\/restart",
            "description": "Parameters application ps restart.",
            "data": [],
            "dataMode": "raw",
            "headerData": null,
            "method": "parameters",
            "pathVariableData": [],
            "queryParams": [],
            "auth": null,
            "events": null,
            "folder": null,
            "protocolProfileBehavior": {
                "disableBodyPruning": true
            },
            "responses": [],
            "currentHelper": null,
            "helperAttributes": null,
            "collectionId": "31651f336377d11d76b7a1ef5e7b457e",
            "rawModeData": ""
        },
        {
            "id": "72a538dbf41311e27013dd558673b114",
            "name": "Add Application PS Restart",
            "url": "httpsapi.heroku.com\/\/apps\/{app}\/ps\/restart",
            "description": "Restart processes of an app. Specify either ps or type to restart only the specified processes. Leave both blank to restart the entire app.",
            "data": [],
            "dataMode": "raw",
            "headerData": null,
            "method": "post",
            "pathVariableData": [],
            "queryParams": [
                {
                    "key": "Accept",
                    "description": "Content type.",
                    "value": "",
                    "equals": true,
                    "enabled": true
                },
                {
                    "key": "Accept",
                    "description": "Content type.",
                    "value": "",
                    "equals": true,
                    "enabled": true
                },
                {
                    "key": "app",
                    "description": "The app name.",
                    "value": "",
                    "equals": true,
                    "enabled": true
                },
                {
                    "key": "app",
                    "description": "",
                    "value": "",
                    "equals": true,
                    "enabled": true
                },
                {
                    "key": "ps",
                    "description": "Only display logs from a given process.",
                    "value": "",
                    "equals": true,
                    "enabled": true
                },
                {
                    "key": "type",
                    "description": "The type of process to restart.",
                    "value": "",
                    "equals": true,
                    "enabled": true
                }
            ],
            "auth": null,
            "events": null,
            "folder": null,
            "protocolProfileBehavior": {
                "disableBodyPruning": true
            },
            "responses": [],
            "currentHelper": null,
            "helperAttributes": null,
            "collectionId": "31651f336377d11d76b7a1ef5e7b457e",
            "rawModeData": ""
        },
        {
            "id": "134386b05ab3a48b403eeb4dafd61f60",
            "name": "Parameters Application PS Stop",
            "url": "httpsapi.heroku.com\/\/apps\/{app}\/ps\/stop",
            "description": "Parameters application ps stop.",
            "data": [],
            "dataMode": "raw",
            "headerData": null,
            "method": "parameters",
            "pathVariableData": [],
            "queryParams": [],
            "auth": null,
            "events": null,
            "folder": null,
            "protocolProfileBehavior": {
                "disableBodyPruning": true
            },
            "responses": [],
            "currentHelper": null,
            "helperAttributes": null,
            "collectionId": "31651f336377d11d76b7a1ef5e7b457e",
            "rawModeData": ""
        },
        {
            "id": "92fc568fb4ce2f4eae48bfa60d9de2a8",
            "name": "Add Application PS Stop",
            "url": "httpsapi.heroku.com\/\/apps\/{app}\/ps\/stop",
            "description": "Stop processes of an app. Specify either ps or type to stop the specified processes.",
            "data": [],
            "dataMode": "raw",
            "headerData": null,
            "method": "post",
            "pathVariableData": [],
            "queryParams": [
                {
                    "key": "Accept",
                    "description": "Content type.",
                    "value": "",
                    "equals": true,
                    "enabled": true
                },
                {
                    "key": "Accept",
                    "description": "Content type.",
                    "value": "",
                    "equals": true,
                    "enabled": true
                },
                {
                    "key": "app",
                    "description": "The app name.",
                    "value": "",
                    "equals": true,
                    "enabled": true
                },
                {
                    "key": "app",
                    "description": "",
                    "value": "",
                    "equals": true,
                    "enabled": true
                },
                {
                    "key": "ps",
                    "description": "Only display logs from a given process.",
                    "value": "",
                    "equals": true,
                    "enabled": true
                },
                {
                    "key": "type",
                    "description": "The type of process to restart.",
                    "value": "",
                    "equals": true,
                    "enabled": true
                }
            ],
            "auth": null,
            "events": null,
            "folder": null,
            "protocolProfileBehavior": {
                "disableBodyPruning": true
            },
            "responses": [],
            "currentHelper": null,
            "helperAttributes": null,
            "collectionId": "31651f336377d11d76b7a1ef5e7b457e",
            "rawModeData": ""
        },
        {
            "id": "76df724acbdc471377fdda2359ec5eff",
            "name": "Parameters Application PS Scale",
            "url": "httpsapi.heroku.com\/\/apps\/{app}\/ps\/scale",
            "description": "Parameters application ps scale.",
            "data": [],
            "dataMode": "raw",
            "headerData": null,
            "method": "parameters",
            "pathVariableData": [],
            "queryParams": [],
            "auth": null,
            "events": null,
            "folder": null,
            "protocolProfileBehavior": {
                "disableBodyPruning": true
            },
            "responses": [],
            "currentHelper": null,
            "helperAttributes": null,
            "collectionId": "31651f336377d11d76b7a1ef5e7b457e",
            "rawModeData": ""
        },
        {
            "id": "138ee2f94a851f9b66cf8cc2ac4454b7",
            "name": "Add Application PS Scale",
            "url": "httpsapi.heroku.com\/\/apps\/{app}\/ps\/scale",
            "description": "Scale processes of an app.",
            "data": [],
            "dataMode": "raw",
            "headerData": null,
            "method": "post",
            "pathVariableData": [],
            "queryParams": [
                {
                    "key": "Accept",
                    "description": "Content type.",
                    "value": "",
                    "equals": true,
                    "enabled": true
                },
                {
                    "key": "Accept",
                    "description": "Content type.",
                    "value": "",
                    "equals": true,
                    "enabled": true
                },
                {
                    "key": "app",
                    "description": "The app name.",
                    "value": "",
                    "equals": true,
                    "enabled": true
                },
                {
                    "key": "app",
                    "description": "",
                    "value": "",
                    "equals": true,
                    "enabled": true
                },
                {
                    "key": "qty",
                    "description": "The desired number of processes of this type.",
                    "value": "",
                    "equals": true,
                    "enabled": true
                },
                {
                    "key": "type",
                    "description": "The type of process to restart.",
                    "value": "",
                    "equals": true,
                    "enabled": true
                }
            ],
            "auth": null,
            "events": null,
            "folder": null,
            "protocolProfileBehavior": {
                "disableBodyPruning": true
            },
            "responses": [],
            "currentHelper": null,
            "helperAttributes": null,
            "collectionId": "31651f336377d11d76b7a1ef5e7b457e",
            "rawModeData": ""
        },
        {
            "id": "fe4c12850f922a47acd5837484c0f6a1",
            "name": "Parameters Application Releases",
            "url": "httpsapi.heroku.com\/\/apps\/{app}\/releases",
            "description": "Parameters application releases.",
            "data": [],
            "dataMode": "raw",
            "headerData": null,
            "method": "parameters",
            "pathVariableData": [],
            "queryParams": [],
            "auth": null,
            "events": null,
            "folder": null,
            "protocolProfileBehavior": {
                "disableBodyPruning": true
            },
            "responses": [],
            "currentHelper": null,
            "helperAttributes": null,
            "collectionId": "31651f336377d11d76b7a1ef5e7b457e",
            "rawModeData": ""
        },
        {
            "id": "d84746938d499a2807058b3bb7522dc6",
            "name": "Get Application Releases",
            "url": "httpsapi.heroku.com\/\/apps\/{app}\/releases",
            "description": "List releases for an app.",
            "data": [],
            "dataMode": "raw",
            "headerData": null,
            "method": "get",
            "pathVariableData": [],
            "queryParams": [
                {
                    "key": "Accept",
                    "description": "Content type.",
                    "value": "",
                    "equals": true,
                    "enabled": true
                },
                {
                    "key": "Accept",
                    "description": "Content type.",
                    "value": "",
                    "equals": true,
                    "enabled": true
                },
                {
                    "key": "app",
                    "description": "The app name.",
                    "value": "",
                    "equals": true,
                    "enabled": true
                },
                {
                    "key": "app",
                    "description": "",
                    "value": "",
                    "equals": true,
                    "enabled": true
                }
            ],
            "auth": null,
            "events": null,
            "folder": null,
            "protocolProfileBehavior": {
                "disableBodyPruning": true
            },
            "responses": [],
            "currentHelper": null,
            "helperAttributes": null,
            "collectionId": "31651f336377d11d76b7a1ef5e7b457e",
            "rawModeData": ""
        },
        {
            "id": "b9de1a6f7925c806b9dd26d770aad682",
            "name": "Add Application Releases",
            "url": "httpsapi.heroku.com\/\/apps\/{app}\/releases",
            "description": "Add application releases.",
            "data": [],
            "dataMode": "raw",
            "headerData": null,
            "method": "post",
            "pathVariableData": [],
            "queryParams": [
                {
                    "key": "Accept",
                    "description": "Content type.",
                    "value": "",
                    "equals": true,
                    "enabled": true
                },
                {
                    "key": "rollback",
                    "description": "The release to which to roll back.",
                    "value": "",
                    "equals": true,
                    "enabled": true
                },
                {
                    "key": "Accept",
                    "description": "Content type.",
                    "value": "",
                    "equals": true,
                    "enabled": true
                },
                {
                    "key": "app",
                    "description": "The app name.",
                    "value": "",
                    "equals": true,
                    "enabled": true
                },
                {
                    "key": "app",
                    "description": "",
                    "value": "",
                    "equals": true,
                    "enabled": true
                }
            ],
            "auth": null,
            "events": null,
            "folder": null,
            "protocolProfileBehavior": {
                "disableBodyPruning": true
            },
            "responses": [],
            "currentHelper": null,
            "helperAttributes": null,
            "collectionId": "31651f336377d11d76b7a1ef5e7b457e",
            "rawModeData": ""
        },
        {
            "id": "ce8b38531737ed22e9bfb4f99f16574d",
            "name": "Parameters Application Releases",
            "url": "httpsapi.heroku.com\/\/apps\/{app}\/releases\/{release}",
            "description": "Parameters application releases.",
            "data": [],
            "dataMode": "raw",
            "headerData": null,
            "method": "parameters",
            "pathVariableData": [],
            "queryParams": [],
            "auth": null,
            "events": null,
            "folder": null,
            "protocolProfileBehavior": {
                "disableBodyPruning": true
            },
            "responses": [],
            "currentHelper": null,
            "helperAttributes": null,
            "collectionId": "31651f336377d11d76b7a1ef5e7b457e",
            "rawModeData": ""
        },
        {
            "id": "98fe7fac3bfa1105c62c5323639a8e3e",
            "name": "Get Application Releases",
            "url": "httpsapi.heroku.com\/\/apps\/{app}\/releases\/{release}",
            "description": "Get application releases.",
            "data": [],
            "dataMode": "raw",
            "headerData": null,
            "method": "get",
            "pathVariableData": [],
            "queryParams": [
                {
                    "key": "Accept",
                    "description": "Content type.",
                    "value": "",
                    "equals": true,
                    "enabled": true
                },
                {
                    "key": "Accept",
                    "description": "Content type.",
                    "value": "",
                    "equals": true,
                    "enabled": true
                },
                {
                    "key": "app",
                    "description": "The app name.",
                    "value": "",
                    "equals": true,
                    "enabled": true
                },
                {
                    "key": "app",
                    "description": "",
                    "value": "",
                    "equals": true,
                    "enabled": true
                },
                {
                    "key": "release",
                    "description": "The release name.",
                    "value": "",
                    "equals": true,
                    "enabled": true
                },
                {
                    "key": "release",
                    "description": "",
                    "value": "",
                    "equals": true,
                    "enabled": true
                }
            ],
            "auth": null,
            "events": null,
            "folder": null,
            "protocolProfileBehavior": {
                "disableBodyPruning": true
            },
            "responses": [],
            "currentHelper": null,
            "helperAttributes": null,
            "collectionId": "31651f336377d11d76b7a1ef5e7b457e",
            "rawModeData": ""
        },
        {
            "id": "6984843f1c35f041de076d5b56ee87f6",
            "name": "Parameters Application Stack",
            "url": "httpsapi.heroku.com\/\/apps\/{app}\/stack",
            "description": "Parameters application stack.",
            "data": [],
            "dataMode": "raw",
            "headerData": null,
            "method": "parameters",
            "pathVariableData": [],
            "queryParams": [],
            "auth": null,
            "events": null,
            "folder": null,
            "protocolProfileBehavior": {
                "disableBodyPruning": true
            },
            "responses": [],
            "currentHelper": null,
            "helperAttributes": null,
            "collectionId": "31651f336377d11d76b7a1ef5e7b457e",
            "rawModeData": ""
        },
        {
            "id": "f787967235c7b73e80768685a6c1f869",
            "name": "Get Application Stack",
            "url": "httpsapi.heroku.com\/\/apps\/{app}\/stack",
            "description": "List available stacks for an app.",
            "data": [],
            "dataMode": "raw",
            "headerData": null,
            "method": "get",
            "pathVariableData": [],
            "queryParams": [
                {
                    "key": "Accept",
                    "description": "Content type.",
                    "value": "",
                    "equals": true,
                    "enabled": true
                },
                {
                    "key": "Accept",
                    "description": "Content type.",
                    "value": "",
                    "equals": true,
                    "enabled": true
                },
                {
                    "key": "app",
                    "description": "The app name.",
                    "value": "",
                    "equals": true,
                    "enabled": true
                },
                {
                    "key": "app",
                    "description": "",
                    "value": "",
                    "equals": true,
                    "enabled": true
                }
            ],
            "auth": null,
            "events": null,
            "folder": null,
            "protocolProfileBehavior": {
                "disableBodyPruning": true
            },
            "responses": [],
            "currentHelper": null,
            "helperAttributes": null,
            "collectionId": "31651f336377d11d76b7a1ef5e7b457e",
            "rawModeData": ""
        },
        {
            "id": "a3a8d0d354b89c12f506bcb4a752f699",
            "name": "Put Application Stack",
            "url": "httpsapi.heroku.com\/\/apps\/{app}\/stack",
            "description": "Migrate an app to a new stack.",
            "data": [],
            "dataMode": "raw",
            "headerData": null,
            "method": "put",
            "pathVariableData": [],
            "queryParams": [
                {
                    "key": "Accept",
                    "description": "Content type.",
                    "value": "",
                    "equals": true,
                    "enabled": true
                },
                {
                    "key": "Accept",
                    "description": "Content type.",
                    "value": "",
                    "equals": true,
                    "enabled": true
                },
                {
                    "key": "app",
                    "description": "The app name.",
                    "value": "",
                    "equals": true,
                    "enabled": true
                },
                {
                    "key": "app",
                    "description": "",
                    "value": "",
                    "equals": true,
                    "enabled": true
                }
            ],
            "auth": null,
            "events": null,
            "folder": null,
            "protocolProfileBehavior": {
                "disableBodyPruning": true
            },
            "responses": [],
            "currentHelper": null,
            "helperAttributes": null,
            "collectionId": "31651f336377d11d76b7a1ef5e7b457e",
            "rawModeData": ""
        }
    ]
}